InstagramIG/SidraTools.py
InstagramIG/__init__.py
InstagramIG-0.0.2.dist-info/LICENSE
InstagramIG-0.0.2.dist-info/METADATA
InstagramIG-0.0.2.dist-info/WHEEL
InstagramIG-0.0.2.dist-info/top_level.txt
InstagramIG-0.0.2.dist-info/RECORD
