Metadata-Version: 2.1
Name: InstagramIG
Version: 0.0.2
Summary: Scrape Instagram Profile and login Instagram
Home-page: https://github.com/SidraELEzz/InstagramIG
Author: SidraELEzz
Author-email: 
License: UNKNOWN
Project-URL: Bug Tracker, https://github.com/pypa/sampleproject/issues
Keywords: instagram
Platform: UNKNOWN
Classifier: Development Status :: 1 - Planning
Classifier: Intended Audience :: Developers
Classifier: Programming Language :: Python :: 3
Classifier: Operating System :: Unix
Classifier: Operating System :: MacOS :: MacOS X
Classifier: Operating System :: Microsoft :: Windows
License-File: LICENSE
Requires-Dist: requests
